animanager/__init__.py
animanager/__main__.py
animanager/anidb.py
animanager/animecmd.py
animanager/cmdlib.py
animanager/config.py
animanager/date.py
animanager/datets.py
animanager/migrations.py
animanager/objects.py
animanager/utils.py
animanager/xml.py
animanager/anidb/__init__.py
animanager/anidb/anime.py
animanager/anidb/http.py
animanager/anidb/titles.py
animanager/animecmd/__init__.py
animanager/animecmd/add.py
animanager/animecmd/addrule.py
animanager/animecmd/asearch.py
animanager/animecmd/bump.py
animanager/animecmd/deleterule.py
animanager/animecmd/fetchtitles.py
animanager/animecmd/gpl.py
animanager/animecmd/helpcmd.py
animanager/animecmd/purgecache.py
animanager/animecmd/quitcmd.py
animanager/animecmd/register.py
animanager/animecmd/reset.py
animanager/animecmd/rules.py
animanager/animecmd/search.py
animanager/animecmd/show.py
animanager/animecmd/unregister.py
animanager/animecmd/update.py
animanager/animecmd/watch.py
animanager/cmd/__init__.py
animanager/cmd/argparse.py
animanager/cmd/cmd.py
animanager/cmd/utils.py
animanager/cmd/results/__init__.py
animanager/cmd/results/aid.py
animanager/cmd/results/results.py
animanager/commands/__init__.py
animanager/commands/add.py
animanager/commands/addrule.py
animanager/commands/asearch.py
animanager/commands/deleterule.py
animanager/commands/fix.py
animanager/commands/gpl.py
animanager/commands/help.py
animanager/commands/purgecache.py
animanager/commands/register.py
animanager/commands/reset.py
animanager/commands/rules.py
animanager/commands/search.py
animanager/commands/show.py
animanager/commands/unregister.py
animanager/commands/update.py
animanager/commands/watch.py
animanager/db/__init__.py
animanager/db/cachetable.py
animanager/db/migrations.py
animanager/db/query/__init__.py
animanager/db/query/collections.py
animanager/db/query/eptype.py
animanager/db/query/files.py
animanager/db/query/select.py
animanager/db/query/status.py
animanager-0.12.0.dist-info/METADATA
animanager-0.12.0.dist-info/RECORD
animanager-0.12.0.dist-info/WHEEL
animanager-0.12.0.dist-info/entry_points.txt
animanager-0.12.0.dist-info/top_level.txt
